README.md
setup.py
sensational/__init__.py
sensational.egg-info/PKG-INFO
sensational.egg-info/SOURCES.txt
sensational.egg-info/dependency_links.txt
sensational.egg-info/top_level.txt
sensational/perceptions/__init__.py
sensational/perceptions/acceleration.py
sensational/perceptions/depth.py
sensational/perceptions/magnetism.py
sensational/perceptions/temperature.py
sensational/perceptions/conceptual/__init__.py
sensational/perceptions/conceptual/axial.py
sensational/sensors/__init__.py
sensational/sensors/abstract/__init__.py
sensational/sensors/abstract/i2c.py
sensational/sensors/i2c/__init__.py
sensational/sensors/i2c/ak8963.py
sensational/sensors/i2c/mpu9250.py
sensational/units/__init__.py
sensational/units/provider.py
sensational/units/factories/__init__.py
sensational/units/factories/factory.py
sensational/units/factories/numerical_units_factory.py
sensational/units/factories/pint_factory.py