Metadata-Version: 2.1
Name: sensational
Version: 0.0.2
Summary: A python library for interfacing with various sensors
Home-page: https://gitlab.com/vectoridau/sensational
Author: Daniel 'Vector' Kerr
Author-email: vector@vector.id.au
License: UNKNOWN
Platform: UNKNOWN
Classifier: Development Status :: 3 - Alpha
Classifier: License :: OSI Approved :: MIT License
Classifier: Natural Language :: English
Classifier: Operating System :: OS Independent
Classifier: Programming Language :: Python :: 3
Classifier: Topic :: System :: Hardware
Classifier: Topic :: Utilities
Requires-Python: >=3
